{
  "itemId": 5799595,
  "name": "Arm & Hammer 9-Pack Odor Eliminating Vacuum Bags, Eureka RR &#153; Premium Allergen",
  "salePrice": 10.31,
  "upc": "023169120716",
  "categoryPath": "Home/Appliances/Vacuums & Floor Care/Vacuum Bags & Accessories",
  "brandName": "Eureka",
  "productTrackingUrl": "http://linksynergy.walmart.com/fs-bin/click?id=|LSNID|&offerid=223073.7200&type=14&catid=8&subid=0&hid=7200&tmpid=1082&RD_PARM1=http%253A%252F%252Fwww.walmart.com%252Fip%252FArm-Hammer-9-Pack-Odor-Eliminating-Vacuum-Bags-Eureka-RR-153-Premium-Allergen%252F5799595%253Faffp1%253Dl1dAKNLrNlFLqxAnUYUMtwzELl3x1lA0ev6C4H5U2XY%2526affilsrc%253Dapi",
  "productUrl": "http://c.affil.walmart.com/t/api06?l=http%3A%2F%2Fwww.walmart.com%2Fip%2FArm-Hammer-9-Pack-Odor-Eliminating-Vacuum-Bags-Eureka-RR-153-Premium-Allergen%2F5799595%3Faffp1%3Dl1dAKNLrNlFLqxAnUYUMtwzELl3x1lA0ev6C4H5U2XY%26affilsrc%3Dapi%26veh%3Daff%26wmlspartner%3Dreadonlyapi",
  "categoryNode": "4044_90548_4047",
  "reviews": [
    {
      "name": "Arm & Hammer 9-Pack Odor Eliminating Vacuum Bags, Eureka RR ™ Premium Allergen",
      "overallRating": {
        "label": "Overall",
        "rating": "5"
      },
      "productAttributes": [
        {
          "label": "Value",
          "rating": "5"
        },
        {
          "label": "Meets Expectations",
          "rating": "5"
        },
        {
          "label": "Durability",
          "rating": "5"
        },
        {
          "label": "Appearance",
          "rating": "5"
        }
      ],
      "reviewer": "mary53925",
      "reviewText": "I had to laugh when they arrived, I know exactly what must have happened to earlier reviewers. YES there are 3 packages in the box. There are 3 bags in each package. I can only assume some of the other reviewers saw 3 packages and assumed each held one bag. My order was site to store and it arrived as promised. A great value compared to picking them up off the shelf in the physical store.",
      "submissionTime": "2013-11-07T04:23:23",
      "title": "Let's count them!",
      "upVotes": "7",
      "downVotes": "0"
    },
    {
      "name": "Arm & Hammer 9-Pack Odor Eliminating Vacuum Bags, Eureka RR ™ Premium Allergen",
      "overallRating": {
        "label": "Overall",
        "rating": "5"
      },
      "productAttributes": [
        {
          "label": "Value",
          "rating": "5"
        },
        {
          "label": "Meets Expectations",
          "rating": "5"
        },
        {
          "label": "Durability",
          "rating": "5"
        },
        {
          "label": "Appearance",
          "rating": "5"
        }
      ],
      "reviewer": "InHisServiceToo",
      "reviewText": "Love these premium bags...they really do help contain the fine dust particles better. The 9-bag-bundle (3 packages of three bags each) is a really good deal. I paid $6 for the last 3-bag pack I bought.",
      "submissionTime": "2013-07-09T11:59:00",
      "title": "Premium Allergen Bags ARE Better",
      "upVotes": "4",
      "downVotes": "0"
    },
    {
      "name": "Arm & Hammer 9-Pack Odor Eliminating Vacuum Bags, Eureka RR ™ Premium Allergen",
      "overallRating": {
        "label": "Overall",
        "rating": "4"
      },
      "productAttributes": [
        {
          "label": "Value",
          "rating": "5"
        },
        {
          "label": "Meets Expectations",
          "rating": "4"
        },
        {
          "label": "Durability",
          "rating": "4"
        },
        {
          "label": "Appearance",
          "rating": "4"
        }
      ],
      "reviewer": "67morgan",
      "reviewText": "Bought the 9 pack. Good value. Now hope the vacum lasts as long as the 9 bags!",
      "submissionTime": "2013-12-27T07:59:52",
      "title": "It's a vacum bag...",
      "upVotes": "3",
      "downVotes": "0"
    },
    {
      "name": "Arm & Hammer 9-Pack Odor Eliminating Vacuum Bags, Eureka RR ™ Premium Allergen",
      "overallRating": {
        "label": "Overall",
        "rating": "1"
      },
      "reviewer": "doccadave",
      "reviewText": "Ordered a 9 pak online. I got a3 pak which is in the store . Had to return it . What an online shopping disappointment.",
      "submissionTime": "2013-05-06T07:15:54",
      "title": "06 May 2013",
      "upVotes": "3",
      "downVotes": "2"
    },
    {
      "name": "Arm & Hammer 9-Pack Odor Eliminating Vacuum Bags, Eureka RR ™ Premium Allergen",
      "overallRating": {
        "label": "Overall",
        "rating": "5"
      },
      "productAttributes": [
        {
          "label": "Value",
          "rating": "5"
        },
        {
          "label": "Meets Expectations",
          "rating": "5"
        },
        {
          "label": "Durability",
          "rating": "5"
        },
        {
          "label": "Appearance",
          "rating": "5"
        }
      ],
      "reviewer": "MY4HAPPYTAILS",
      "reviewText": "I USUALLY BUY THESE BAGS IN THE STORE BUT I ORDERED THEM ONLINE THIS TIME . THEY ARRIVED QUICKLY AND WERE JUST AS DISCRIBED ..I WILL CONTINUE TO BUY THESE ONLINE ..MUCH EASIER",
      "submissionTime": "2013-04-05T10:04:34",
      "title": "VACUUM BAGS",
      "upVotes": "2",
      "downVotes": "1"
    }
  ],
  "reviewStatistics": {
    "averageOverallRating": "4.53",
    "overallRatingRange": "5",
    "ratingDistributions": [
      {
        "count": "2",
        "ratingValue": "1"
      },
      {
        "count": "1",
        "ratingValue": "2"
      },
      {
        "count": "6",
        "ratingValue": "4"
      },
      {
        "count": "27",
        "ratingValue": "5"
      }
    ],
    "totalReviewCount": "36"
  },
  "availableOnline": true
}
