{
  "itemId": 41509259,
  "name": "Samsung WB50F Smart Digital Camera (Red) with 32GB Deluxe Accessory Kit",
  "salePrice": 189,
  "upc": "616320845193",
  "categoryPath": "Electronics/Cameras & Camcorders/Point & Shoot Cameras",
  "brandName": "Samsung",
  "productTrackingUrl": "http://linksynergy.walmart.com/fs-bin/click?id=|LSNID|&offerid=223073.7200&type=14&catid=8&subid=0&hid=7200&tmpid=1082&RD_PARM1=http%253A%252F%252Fwww.walmart.com%252Fip%252FSamsung-WB50F-Smart-Digital-Camera-Red-with-32GB-Deluxe-Accessory-Kit%252F41509259%253Faffp1%253Dl1dAKNLrNlFLqxAnUYUMtwzELl3x1lA0ev6C4H5U2XY%2526affilsrc%253Dapi",
  "productUrl": "http://c.affil.walmart.com/t/api06?l=http%3A%2F%2Fwww.walmart.com%2Fip%2FSamsung-WB50F-Smart-Digital-Camera-Red-with-32GB-Deluxe-Accessory-Kit%2F41509259%3Faffp1%3Dl1dAKNLrNlFLqxAnUYUMtwzELl3x1lA0ev6C4H5U2XY%26affilsrc%3Dapi%26veh%3Daff%26wmlspartner%3Dreadonlyapi",
  "categoryNode": "3944_133277_1166834",
  "reviews": [
    {
      "name": "Samsung WB50F Smart Digital Camera (Red) with 32GB Deluxe Accessory Kit",
      "overallRating": {
        "label": "Overall",
        "rating": "5"
      },
      "productAttributes": [
        {
          "label": "Features",
          "rating": "5"
        },
        {
          "label": "Value",
          "rating": "5"
        }
      ],
      "reviewer": "funcamera",
      "reviewText": "I love this easy to use camera and the sharing WiFi features just add to the cameras easy-to-use features. The live panoramic feature is another excellent feature.",
      "submissionTime": "2015-02-22T12:43:06",
      "title": "excellent point and shoot",
      "upVotes": "0",
      "downVotes": "0"
    },
    {
      "name": "Samsung WB50F Smart Digital Camera (Red) with 32GB Deluxe Accessory Kit",
      "overallRating": {
        "label": "Overall",
        "rating": "5"
      },
      "productAttributes": [
        {
          "label": "Features",
          "rating": "5"
        },
        {
          "label": "Value",
          "rating": "5"
        }
      ],
      "reviewer": "Netboss1",
      "reviewText": "We have been waiting to buy a camera like this for a long time. We are busy with the social network and this camera has all of the features one could want, to share and save with all of your phones and computers. This Rocks!",
      "submissionTime": "2014-05-09T18:24:35",
      "title": "Great Camera",
      "upVotes": "0",
      "downVotes": "0"
    },
    {
      "name": "Samsung WB50F Smart Digital Camera (Red) with 32GB Deluxe Accessory Kit",
      "overallRating": {
        "label": "Overall",
        "rating": "5"
      },
      "productAttributes": [
        {
          "label": "Features",
          "rating": "5"
        },
        {
          "label": "Value",
          "rating": "5"
        }
      ],
      "reviewer": "Gampy",
      "reviewText": "I've wanted a really good camera to replace my older digital camera. I tried other cameras and were disappointed........until I bought my Samsung. It has everything I wanted and at a great price. Try it, you'll like it!",
      "submissionTime": "2015-01-23T20:48:05",
      "title": "Great Photography with my Samsung",
      "upVotes": "0",
      "downVotes": "0"
    }
  ],
  "reviewStatistics": {
    "averageOverallRating": "5.0",
    "overallRatingRange": "5",
    "ratingDistributions": [
      {
        "count": "3",
        "ratingValue": "5"
      }
    ],
    "totalReviewCount": "3"
  },
  "availableOnline": true
}
