{
  "itemId": 17479952,
  "name": "Tim Tebow: Everything In Between (Anamorphic Widescreen)",
  "salePrice": 11.92,
  "upc": "025192112997",
  "categoryPath": "Movies & TV/TV Shows/Sports/Football",
  "productTrackingUrl": "http://linksynergy.walmart.com/fs-bin/click?id=|LSNID|&offerid=223073.7200&type=14&catid=8&subid=0&hid=7200&tmpid=1082&RD_PARM1=http%253A%252F%252Fwww.walmart.com%252Fip%252FTim-Tebow-Everything-In-Between-Anamorphic-Widescreen%252F17479952%253Faffp1%253Dl1dAKNLrNlFLqxAnUYUMtwzELl3x1lA0ev6C4H5U2XY%2526affilsrc%253Dapi",
  "productUrl": "http://c.affil.walmart.com/t/api06?l=http%3A%2F%2Fwww.walmart.com%2Fip%2FTim-Tebow-Everything-In-Between-Anamorphic-Widescreen%2F17479952%3Faffp1%3Dl1dAKNLrNlFLqxAnUYUMtwzELl3x1lA0ev6C4H5U2XY%26affilsrc%3Dapi%26veh%3Daff%26wmlspartner%3Dreadonlyapi",
  "categoryNode": "4096_530719_530717",
  "reviews": [
    {
      "name": "Tim Tebow: Everything In Between (Anamorphic Widescreen)",
      "overallRating": {
        "label": "Overall",
        "rating": "5"
      },
      "productAttributes": [
        {
          "label": "Value",
          "rating": "5"
        },
        {
          "label": "Meets Expectations",
          "rating": "5"
        }
      ],
      "reviewer": "kleng",
      "reviewText": "The video's very uplifting. A simple person turned into a phenomenal hero because of his faith towards the Lord Jesus!",
      "submissionTime": "2011-12-17T20:05:13",
      "title": "17 December 2011",
      "upVotes": "10",
      "downVotes": "0"
    },
    {
      "name": "Tim Tebow: Everything In Between (Anamorphic Widescreen)",
      "overallRating": {
        "label": "Overall",
        "rating": "5"
      },
      "productAttributes": [
        {
          "label": "Value",
          "rating": "5"
        },
        {
          "label": "Meets Expectations",
          "rating": "5"
        }
      ],
      "reviewer": "PColaReview",
      "reviewText": "An excellent documentary and inside look at the life of Tim Tebow as he trains to become an NFL quarterback. You will not be disappointed!",
      "submissionTime": "2011-12-31T18:25:57",
      "title": "A must-have inspirational video",
      "upVotes": "3",
      "downVotes": "0"
    },
    {
      "name": "Tim Tebow: Everything In Between (Anamorphic Widescreen)",
      "overallRating": {
        "label": "Overall",
        "rating": "5"
      },
      "productAttributes": [
        {
          "label": "Value",
          "rating": "5"
        },
        {
          "label": "Meets Expectations",
          "rating": "5"
        }
      ],
      "reviewer": "Baboosky",
      "reviewText": "Great documentary",
      "submissionTime": "2012-01-16T13:24:54",
      "title": "Great documentary",
      "upVotes": "0",
      "downVotes": "0"
    }
  ],
  "reviewStatistics": {
    "averageOverallRating": "5.0",
    "overallRatingRange": "5",
    "ratingDistributions": [
      {
        "count": "4",
        "ratingValue": "5"
      }
    ],
    "totalReviewCount": "4"
  },
  "availableOnline": true
}
