{
  "itemId": 21292525,
  "name": "Trademark Fine Art \"Elongated Window\" Canvas Wall Art by Joval",
  "salePrice": 29.93,
  "upc": "886511081871",
  "categoryPath": "Home/Decor/Art & Wall Decor/Canvas Wall Art",
  "brandName": "Trademark Fine Art",
  "productTrackingUrl": "http://linksynergy.walmart.com/fs-bin/click?id=|LSNID|&offerid=223073.7200&type=14&catid=8&subid=0&hid=7200&tmpid=1082&RD_PARM1=http%253A%252F%252Fwww.walmart.com%252Fip%252FTrademark-Art-Elongated-Window-Canvas-Wall-Art-by-Joval%252F21292525%253Faffp1%253Dl1dAKNLrNlFLqxAnUYUMtwzELl3x1lA0ev6C4H5U2XY%2526affilsrc%253Dapi",
  "productUrl": "http://c.affil.walmart.com/t/api06?l=http%3A%2F%2Fwww.walmart.com%2Fip%2FTrademark-Art-Elongated-Window-Canvas-Wall-Art-by-Joval%2F21292525%3Faffp1%3Dl1dAKNLrNlFLqxAnUYUMtwzELl3x1lA0ev6C4H5U2XY%26affilsrc%3Dapi%26veh%3Daff%26wmlspartner%3Dreadonlyapi",
  "categoryNode": "4044_133012_1045881",
  "reviews": [
    {
      "name": "Trademark Fine Art \"Elongated Window\" Canvas Wall Art by Joval",
      "overallRating": {
        "label": "Overall",
        "rating": "5"
      },
      "productAttributes": [
        {
          "label": "Value",
          "rating": "5"
        },
        {
          "label": "Meets Expectations",
          "rating": "5"
        }
      ],
      "reviewer": "NorthernCA1",
      "reviewText": "We originally saw this picture through another site many months ago did not get it and then regretted it started looking for it and although it was available on many sights you had the best price and the added surprise for me was I did not know you had so many things like this picture available on line that I can't get in my store but can have it delivered to my store at no extra cost, very pleased with my purchase and it looks great in my room thank you",
      "submissionTime": "2014-05-02T20:08:18",
      "title": "LOVE IT",
      "upVotes": "3",
      "downVotes": "0"
    },
    {
      "name": "Trademark Fine Art \"Elongated Window\" Canvas Wall Art by Joval",
      "overallRating": {
        "label": "Overall",
        "rating": "4"
      },
      "productAttributes": [
        {
          "label": "Value",
          "rating": "4"
        },
        {
          "label": "Meets Expectations",
          "rating": "4"
        },
        {
          "label": "Appearance",
          "rating": "4"
        }
      ],
      "reviewer": "Chicky2454",
      "reviewText": "My kitchen does not have a window and I was looking for a picture that would seem like I was l looking out the window onto the ocean. This painting does the job! Very peaceful and welcoming.",
      "submissionTime": "2013-08-15T02:29:30",
      "title": "Like looking out a window",
      "upVotes": "2",
      "downVotes": "0"
    },
    {
      "name": "Trademark Fine Art \"Elongated Window\" Canvas Wall Art by Joval",
      "overallRating": {
        "label": "Overall",
        "rating": "5"
      },
      "productAttributes": [
        {
          "label": "Value",
          "rating": "5"
        },
        {
          "label": "Meets Expectations",
          "rating": "5"
        }
      ],
      "reviewer": "BackPainVictim",
      "reviewText": "In the pictures online, the painting's colors look faded. When I received this in the mail, I was pleased to see that the saturation was much more vibrant than what we see online! I don't have a window on one wall of my living room, so that was the perfect spot for this painting!",
      "submissionTime": "2014-07-21T08:01:25",
      "title": "Just Beautiful!",
      "upVotes": "1",
      "downVotes": "0"
    },
    {
      "name": "Trademark Fine Art \"Elongated Window\" Canvas Wall Art by Joval",
      "overallRating": {
        "label": "Overall",
        "rating": "5"
      },
      "reviewer": "candijo73",
      "reviewText": "Very pretty picture",
      "submissionTime": "2014-11-18T07:41:19",
      "title": "Beach scene",
      "upVotes": "0",
      "downVotes": "0"
    }
  ],
  "reviewStatistics": {
    "averageOverallRating": "4.75",
    "overallRatingRange": "5",
    "ratingDistributions": [
      {
        "count": "1",
        "ratingValue": "4"
      },
      {
        "count": "3",
        "ratingValue": "5"
      }
    ],
    "totalReviewCount": "4"
  },
  "availableOnline": true
}
